notebookforms/__about__.py
notebookforms/__init__.py
notebookforms/formHandler.py
notebookforms/items.py
notebookforms-0.1.1.dist-info/METADATA
notebookforms-0.1.1.dist-info/WHEEL
notebookforms-0.1.1.dist-info/RECORD
